Metadata-Version: 2.1
Name: ncnn-vulkan
Version: 2023.6.18
Summary: ncnn is a high-performance neural network inference framework optimized for the mobile platform
Home-page: https://github.com/joeyballentine/ncnn-vulkan
Author: nihui
Author-email: nihuini@tencent.com
Maintainer: caishanli
Maintainer-email: caishanli25@gmail.com
License: BSD-3
Classifier: Programming Language :: C++
Classifier: Programming Language :: Python :: 3
Classifier: Programming Language :: Python :: 3.6
Classifier: Programming Language :: Python :: 3.7
Classifier: Programming Language :: Python :: 3.8
Classifier: Programming Language :: Python :: 3.9
Classifier: Programming Language :: Python :: 3.10
Classifier: License :: OSI Approved :: BSD License
Classifier: Operating System :: OS Independent
Requires-Python: >=3.5
License-File: LICENSE.txt
Requires-Dist: numpy
Requires-Dist: tqdm
Requires-Dist: requests
Requires-Dist: portalocker
Requires-Dist: opencv-python
